pyblnet/__init__.py
pyblnet/blnet.py
pyblnet/blnet_conn.py
pyblnet/blnet_parser.py
pyblnet/blnet_web.py
pyblnet-0.10.0.dist-info/licenses/LICENSE.txt
pyblnet-0.10.0.dist-info/WHEEL
pyblnet-0.10.0.dist-info/METADATA
pyblnet-0.10.0.dist-info/RECORD
