Metadata-Version: 2.4
Name: PyBLNET
Version: 0.10.0
Summary: Automate wireless communication to UVR1611 via BL-NET
Keywords: python,uvr1611,blnet,technische alternative,home automation,iot
Author-email: nielstron <n.muendler@posteo.de>
Requires-Python: >=3
Classifier: Development Status :: 4 - Beta
Classifier: Intended Audience :: Developers
Classifier: Topic :: Software Development :: Object Brokering
Classifier: License :: OSI Approved :: MIT License
Classifier: Programming Language :: Python :: 3.8
Classifier: Programming Language :: Python :: 3.9
Classifier: Programming Language :: Python :: 3.10
Classifier: Programming Language :: Python :: 3.11
Classifier: Programming Language :: Python :: 3.12
Classifier: Programming Language :: Python :: 3.13
License-File: LICENSE.txt
Requires-Dist: htmldom
Requires-Dist: requests
Requires-Dist: pytest ; extra == "test"
Project-URL: Homepage, https://github.com/nielstron/pyblnet/
Provides-Extra: test
